bus_station/__init__.py
bus_station/bus_stop/__init__.py
bus_station/bus_stop/bus_stop.py
bus_station/bus_stop/registration/__init__.py
bus_station/bus_stop/registration/address/__init__.py
bus_station/bus_stop/registration/address/address_not_found_for_passenger.py
bus_station/bus_stop/registration/address/bus_stop_address_registry.py
bus_station/bus_stop/registration/address/redis_bus_stop_address_registry.py
bus_station/bus_stop/registration/bus_stop_registry.py
bus_station/command_terminal/__init__.py
bus_station/command_terminal/bus/__init__.py
bus_station/command_terminal/bus/asynchronous/__init__.py
bus_station/command_terminal/bus/asynchronous/distributed/__init__.py
bus_station/command_terminal/bus/asynchronous/distributed/kombu_command_bus.py
bus_station/command_terminal/bus/asynchronous/memory_queue_command_bus.py
bus_station/command_terminal/bus/asynchronous/threaded_command_bus.py
bus_station/command_terminal/bus/command_bus.py
bus_station/command_terminal/bus/synchronous/__init__.py
bus_station/command_terminal/bus/synchronous/distributed/__init__.py
bus_station/command_terminal/bus/synchronous/distributed/json_rpc_command_bus.py
bus_station/command_terminal/bus/synchronous/distributed/rpyc_command_bus.py
bus_station/command_terminal/bus/synchronous/sync_command_bus.py
bus_station/command_terminal/bus_engine/__init__.py
bus_station/command_terminal/bus_engine/json_rpc_command_bus_engine.py
bus_station/command_terminal/bus_engine/kombu_command_bus_engine.py
bus_station/command_terminal/bus_engine/memory_queue_command_bus_engine.py
bus_station/command_terminal/bus_engine/rpyc_command_bus_engine.py
bus_station/command_terminal/command.py
bus_station/command_terminal/command_execution_failed.py
bus_station/command_terminal/command_handler.py
bus_station/command_terminal/command_handler_not_found.py
bus_station/command_terminal/command_handler_registry.py
bus_station/command_terminal/handler_not_found_for_command.py
bus_station-7.2.0.dist-info/METADATA
bus_station-7.2.0.dist-info/WHEEL
bus_station-7.2.0.dist-info/RECORD
