Metadata-Version: 2.1
Name: bus-station
Version: 7.2.0
Summary: A python bus station
Author: DeejayRevok
Author-email: seryi_one@hotmail.com
Requires-Python: >=3.10.0,<3.11.0
Classifier: Programming Language :: Python :: 3
Classifier: Programming Language :: Python :: 3.10
Provides-Extra: tracking
Requires-Dist: confluent-kafka (>=2.1.1,<3.0.0) ; extra == "tracking"
Requires-Dist: freezegun (>=1.2.2,<2.0.0)
Requires-Dist: jsonrpcclient (>=4.0.3,<5.0.0)
Requires-Dist: jsonrpcserver (>=5.0.9,<6.0.0)
Requires-Dist: kombu (==5.2.2)
Requires-Dist: redis (==4.4.4)
Requires-Dist: requests (>=2.27.1,<3.0.0)
Requires-Dist: rpyc (>=5.3.1,<6.0.0)
